pyauthtools/__init__.py
pyauthtools/jwtauthtool.py
pyauthtools-0.2.8.dist-info/License
pyauthtools-0.2.8.dist-info/METADATA
pyauthtools-0.2.8.dist-info/WHEEL
pyauthtools-0.2.8.dist-info/top_level.txt
pyauthtools-0.2.8.dist-info/RECORD
