Metadata-Version: 2.2
Name: pyauthtools
Version: 0.2.8
Summary: Some auth tools using in python flask.
Author-email: lidaning <453882101@qq.com>
Project-URL: Homepage, https://github.com/relidaning/pyauthtools
Project-URL: Bug Tracker, https://github.com/relidaning/pyauthtools/issues
Classifier: Programming Language :: Python :: 3
Classifier: Operating System :: OS Independent
Requires-Python: >=3.7
License-File: License
